CHANGES.rst
README.rst
bootstrap.py
buildout.cfg
setup.py
src/buildout/__init__.py
src/buildout.sendpickedversions.egg-info/PKG-INFO
src/buildout.sendpickedversions.egg-info/SOURCES.txt
src/buildout.sendpickedversions.egg-info/dependency_links.txt
src/buildout.sendpickedversions.egg-info/entry_points.txt
src/buildout.sendpickedversions.egg-info/namespace_packages.txt
src/buildout.sendpickedversions.egg-info/not-zip-safe
src/buildout.sendpickedversions.egg-info/requires.txt
src/buildout.sendpickedversions.egg-info/top_level.txt
src/buildout/sendpickedversions/__init__.py
src/buildout/sendpickedversions/pickedversions.txt
src/buildout/sendpickedversions/tests.py
src/buildout/sendpickedversions/wrappers.py