Metadata-Version: 1.1
Name: buildout.sendpickedversions
Version: 1.0-alpha.1
Summary: Sends picked packages and versions to a whiskers server.
Home-page: http://github.com/collective/buildout.sendpickedversions
Author: Jukka Ojaniemi
Author-email: jukka.ojaniemi@jyu.fi
License: GPL
Keywords: buildout extension send picked versions
Platform: UNKNOWN
Classifier: Framework :: Buildout
Classifier: Intended Audience :: Developers
Classifier: Topic :: Software Development :: Build Tools
Classifier: Topic :: Software Development :: Libraries :: Python Modules
